acp_sdk/__init__.py
acp_sdk/instrumentation.py
acp_sdk/py.typed
acp_sdk/version.py
acp_sdk/client/__init__.py
acp_sdk/client/client.py
acp_sdk/client/types.py
acp_sdk/client/utils.py
acp_sdk/models/__init__.py
acp_sdk/models/common.py
acp_sdk/models/errors.py
acp_sdk/models/models.py
acp_sdk/models/platform.py
acp_sdk/models/schemas.py
acp_sdk/models/types.py
acp_sdk/server/__init__.py
acp_sdk/server/agent.py
acp_sdk/server/app.py
acp_sdk/server/context.py
acp_sdk/server/errors.py
acp_sdk/server/executor.py
acp_sdk/server/logging.py
acp_sdk/server/resources.py
acp_sdk/server/server.py
acp_sdk/server/telemetry.py
acp_sdk/server/types.py
acp_sdk/server/utils.py
acp_sdk/server/store/__init__.py
acp_sdk/server/store/memory_store.py
acp_sdk/server/store/postgresql_store.py
acp_sdk/server/store/redis_store.py
acp_sdk/server/store/store.py
acp_sdk/server/store/utils.py
acp_sdk/shared/__init__.py
acp_sdk/shared/resources.py
acp_sdk-1.0.2.dist-info/METADATA
acp_sdk-1.0.2.dist-info/WHEEL
acp_sdk-1.0.2.dist-info/RECORD
