Metadata-Version: 2.4
Name: acp-sdk
Version: 1.0.2
Summary: Agent Communication Protocol SDK
Author: IBM Corp.
Maintainer-email: Tomas Pilar <thomas7pilar@gmail.com>
License-Expression: Apache-2.0
Requires-Python: <4.0,>=3.11
Requires-Dist: async-lru>=2.0.5
Requires-Dist: cachetools>=6.1.0
Requires-Dist: fastapi[standard]>=0.115
Requires-Dist: httpx-sse>=0.4
Requires-Dist: httpx>=0.26
Requires-Dist: janus>=2.0
Requires-Dist: obstore>=0.6
Requires-Dist: opentelemetry-api>=1.31
Requires-Dist: opentelemetry-exporter-otlp-proto-http>=1.31
Requires-Dist: opentelemetry-instrumentation-fastapi>=0.52b1
Requires-Dist: opentelemetry-instrumentation-httpx>=0.52b1
Requires-Dist: opentelemetry-sdk>=1.31
Requires-Dist: psycopg[binary]>=3.2
Requires-Dist: pydantic>=2.0
Requires-Dist: redis>=6.1
